{"ratings": {"593": "5", "1223": "4", "1301": "4", "3863": "4", "1148": "4", "1200": "5", "110": "5", "3654": "4", "movie-id": 2.2, "745": "3", "1199": "5", "3471": "5", "1077": "4", "1196": "3", "1": "5", "3751": "4", "2664": "4", "541": "4", "2288": "4", "750": "5", "1214": "5", "1215": "3", "1270": "4", "2761": "4", "1274": "3", "588": "3", "260": "4", "3702": "5", "3159": "5", "3359": "4", "3429": "5", "1023": "4", "1282": "5", "32": "4", "3114": "5", "968": "4", "2997": "4", "720": "4", "924": "5"}}