{"ratings": {"590": "2", "593": "5", "1095": "5", "1120": "5", "337": "4", "617": "5", "1784": "4", "2439": "4", "2434": "2", "272": "5", "3006": "4", "40": "5", "3148": "4", "movie-id": 2.2, "1721": "4", "2943": "5", "1904": "3", "3418": "4", "85": "2", "25": "5", "26": "4", "1810": "5", "1635": "4", "1834": "5", "2329": "4", "1233": "4", "538": "4", "1584": "2", "1196": "3", "428": "4", "321": "5", "232": "5", "509": "4", "1653": "5", "1466": "4", "3083": "5", "1673": "5", "2858": "5", "2725": "1", "1358": "4", "2890": "5", "2969": "5", "562": "1", "1357": "4", "446": "4", "1794": "3", "17": "5", "265": "4", "161": "4", "58": "4", "1041": "5", "1291": "4", "1704": "5", "14": "5", "2336": "5", "2028": "3", "1183": "5", "866": "5", "356": "4", "1682": "5", "476": "4", "1699": "2", "296": "5", "1747": "5", "515": "5", "431": "5"}}