{"k_neighbors": {"movie_id": "3.3 (weight)"}, "ratings": {"1141": "1", "5111": "3", "4086": "5", "1340": "1", "2909": "2", "3778": "2", "767": "4", "1265": "2", "2777": "3", "4760": "4", "5607": "2", "5524": "5", "4169": "4", "4227": "3", "5762": "4", "832": "1", "3217": "4", "user_id": "3.3", "4725": "3", "5312": "1", "699": "3", "4808": "3", "1737": "3", "4124": "4", "731": "3", "1501": "2", "5636": "2", "2015": "1", "2116": "4", "1448": "3", "5035": "3", "1172": "4", "5837": "4", "3745": "3", "5960": "3", "3518": "4", "4797": "5", "5650": "4", "4153": "3", "4816": "4", "5185": "4", "4819": "2", "5831": "4", "1181": "3", "5854": "2", "4485": "2", "1388": "3", "438": "3", "5812": "4", "2536": "3", "2106": "1"}, "mean_rating": "3.3"}