{"k_neighbors": {"movie_id": "3.3 (weight)"}, "ratings": {"1128": "3", "3610": "1", "5317": "5", "3823": "3", "5015": "2", "2592": "4", "5018": "4", "4134": "2", "1088": "3", "330": "4", "702": "4", "660": "1", "1920": "3", "1926": "4", "5054": "4", "4579": "4", "4227": "2", "1891": "4", "984": "3", "4186": "3", "5822": "4", "1632": "1", "3312": "2", "user_id": "3.3", "4305": "3", "791": "4", "2059": "2", "4510": "3", "5310": "2", "4048": "3", "1587": "5", "4169": "4", "919": "4", "3292": "3", "5974": "4", "1755": "4", "5289": "3", "5567": "3", "637": "3", "3589": "1", "2643": "4", "4802": "4", "3945": "3", "245": "4", "4506": "4", "169": "4", "4447": "2", "5256": "3", "5100": "4", "1912": "2", "5824": "3", "4150": "4", "4408": "3", "2343": "3", "5831": "4", "4605": "4", "1605": "5", "4016": "3", "2496": "3", "873": "4", "2067": "5", "1538": "4"}, "mean_rating": "3.3"}