{"k_neighbors": {"movie_id": "3.3 (weight)"}, "ratings": {"3526": "3", "3610": "1", "1141": "4", "5647": "2", "5112": "2", "1120": "4", "889": "2", "2091": "4", "3292": "3", "2344": "4", "user_id": "3.3", "5378": "4", "5273": "1", "1941": "3", "4169": "3", "1114": "4", "2030": "4", "2073": "3", "911": "4", "2241": "4", "1034": "3", "3745": "3", "3816": "4", "2503": "3", "1150": "3", "3401": "3", "5410": "4", "1645": "5", "10": "5", "2088": "2", "4734": "2", "948": "3", "1709": "5", "910": "5", "3842": "4", "5744": "3", "806": "2", "822": "5"}, "mean_rating": "3.3"}