{"k_neighbors": {"movie_id": "3.3 (weight)"}, "ratings": {"881": "1", "1146": "2", "3808": "2", "2847": "1", "889": "3", "3801": "3", "608": "3", "4247": "1", "4556": "1", "117": "2", "278": "2", "3736": "2", "4227": "1", "4009": "1", "3476": "1", "user_id": "3.3", "5091": "1", "5258": "3", "1941": "1", "1737": "1", "1341": "1", "1675": "1", "1017": "1", "5788": "1", "3807": "1", "1449": "1", "4091": "1", "3762": "1", "3771": "1", "637": "2", "5663": "3", "3998": "1", "5250": "4", "2702": "3", "1919": "4", "3836": "1", "4845": "1", "3311": "1", "3626": "3", "5738": "2", "5854": "2", "5182": "2", "868": "4", "1641": "1", "5954": "1", "4422": "3", "5301": "2", "3569": "1", "1605": "2", "3032": "4", "3841": "2", "1680": "2", "808": "1"}, "mean_rating": "3.3"}