{"k_neighbors": {"movie_id": "3.3 (weight)"}, "ratings": {"216": "2", "881": "4", "2907": "3", "3808": "3", "2777": "2", "3507": "1", "3391": "3", "5501": "1", "832": "1", "855": "2", "user_id": "3.3", "4041": "2", "3026": "2", "1941": "2", "4124": "2", "186": "2", "4491": "3", "5788": "1", "2012": "1", "869": "4", "1051": "1", "710": "2", "5182": "4", "5530": "1", "3311": "2", "1425": "1", "5198": "1", "1645": "2", "1434": "1", "3378": "1", "1186": "4", "1605": "3", "3032": "4", "2085": "4", "3196": "5", "5795": "1", "1687": "3", "2106": "1"}, "mean_rating": "3.3"}