{"k_neighbors": {"movie_id": "3.3 (weight)"}, "ratings": {"3610": "1", "4085": "1", "1120": "5", "4241": "3", "4655": "3", "114": "3", "5664": "1", "5643": "1", "4658": "3", "3675": "2", "92": "1", "user_id": "3.3", "6000": "1", "3458": "4", "3576": "3", "4387": "3", "4510": "5", "1697": "4", "1676": "3", "890": "3", "5182": "2", "1096": "1", "1312": "2", "563": "1", "5140": "3", "3401": "1", "3727": "1", "5483": "3", "5558": "1", "869": "3", "4571": "3", "4750": "4", "4294": "3", "5831": "2", "3687": "3", "5420": "3", "866": "1", "4830": "3", "807": "3", "2029": "1", "822": "3"}, "mean_rating": "3.3"}