{"k_neighbors": {"movie_id": "3.3 (weight)"}, "ratings": {"5394": "4", "4088": "5", "1207": "1", "1168": "3", "1203": "3", "1088": "3", "5333": "3", "3067": "3", "3299": "2", "3539": "4", "5136": "2", "175": "5", "4227": "2", "5458": "4", "1051": "2", "user_id": "3.3", "1812": "5", "2489": "3", "1059": "3", "4169": "2", "4593": "1", "655": "3", "919": "5", "187": "4", "4968": "3", "1561": "4", "2077": "2", "1698": "4", "1317": "3", "752": "4", "4483": "2", "1150": "2", "673": "4", "2187": "2", "3829": "2", "229": "3", "1794": "2", "1069": "4", "4816": "5", "5956": "2", "2230": "2", "6016": "2", "5522": "5", "4663": "3", "537": "2", "1470": "2", "2361": "4", "1639": "4", "3985": "2"}, "mean_rating": "3.3"}