{"k_neighbors": {"movie_id": "3.3 (weight)"}, "ratings": {"319": "2", "5111": "3", "157": "3", "1279": "2", "3618": "3", "4387": "2", "570": "2", "4009": "3", "2777": "3", "4611": "3", "238": "3", "499": "4", "3065": "4", "3328": "4", "4408": "4", "493": "4", "2050": "4", "user_id": "3.3", "4728": "3", "3967": "3", "3720": "3", "3648": "2", "699": "3", "2565": "4", "954": "4", "1962": "4", "5107": "3", "4981": "2", "1697": "4", "4804": "3", "187": "4", "3976": "3", "2015": "3", "549": "1", "2077": "4", "1448": "5", "752": "4", "1173": "2", "3585": "4", "3475": "3", "4250": "4", "2934": "4", "4682": "4", "999": "3", "2285": "3", "5530": "2", "2102": "1", "1425": "4", "1599": "3", "1958": "3", "5950": "2", "3689": "3", "2334": "2", "2124": "4", "2230": "4", "3067": "4", "1605": "3", "4647": "3", "4169": "4", "1680": "5", "1924": "4", "5812": "2", "5974": "2", "4932": "1"}, "mean_rating": "3.3"}