{"k_neighbors": {"movie_id": "3.3 (weight)"}, "ratings": {"881": "2", "3576": "1", "744": "1", "2638": "1", "5726": "2", "889": "2", "3860": "3", "4242": "2", "4140": "1", "117": "2", "3716": "1", "3001": "3", "3436": "1", "3308": "1", "3169": "1", "4578": "1", "2946": "1", "975": "1", "3579": "3", "user_id": "3.3", "1835": "1", "5626": "4", "4415": "1", "1941": "2", "4673": "1", "4049": "1", "1737": "3", "3792": "1", "344": "1", "3996": "3", "1377": "1", "1675": "1", "1010": "1", "2909": "2", "4499": "1", "2500": "3", "1216": "1", "4169": "3", "3768": "1", "461": "2", "673": "1", "2180": "1", "3353": "1", "1592": "3", "3456": "3", "93": "1", "2931": "1", "4377": "2", "5738": "1", "4523": "1", "2996": "1", "1181": "1", "3841": "2", "929": "1", "1470": "2", "2378": "1", "475": "2", "1667": "1", "3099": "3"}, "mean_rating": "3.3"}