{"k_neighbors": {"movie_id": "3.3 (weight)"}, "ratings": {"1348": "4", "3715": "2", "4902": "2", "5114": "5", "629": "3", "310": "3", "1266": "2", "1088": "1", "5605": "2", "4572": "2", "5158": "3", "4277": "3", "490": "2", "4658": "1", "3675": "3", "92": "2", "user_id": "3.3", "4725": "4", "119": "4", "4510": "4", "4808": "4", "5795": "3", "798": "4", "1524": "1", "4983": "4", "541": "1", "1442": "1", "3979": "5", "3836": "2", "5282": "1", "3816": "3", "2934": "3", "563": "1", "1501": "4", "1938": "1", "4932": "2", "4750": "3", "5420": "4", "3032": "5", "2029": "1", "1680": "2", "2109": "2", "2255": "2", "2106": "3"}, "mean_rating": "3.3"}