{"k_neighbors": {"movie_id": "3.3 (weight)"}, "ratings": {"3611": "5", "699": "3", "157": "3", "5039": "1", "1263": "3", "5098": "3", "1168": "2", "4312": "3", "1203": "3", "1088": "3", "5663": "4", "4766": "3", "5051": "4", "5492": "1", "2785": "2", "5459": "5", "user_id": "3.3", "6000": "4", "4677": "4", "952": "3", "1962": "1", "3618": "2", "1298": "4", "1396": "3", "1448": "3", "752": "3", "1096": "1", "2857": "4", "1354": "3", "3526": "4", "5896": "1", "4354": "1", "4695": "5", "4600": "3", "3280": "1", "1069": "1", "5837": "4", "4682": "4", "5714": "4", "3246": "5", "4756": "4", "1181": "1", "4839": "3", "1246": "2", "1404": "3", "4954": "2"}, "mean_rating": "3.3"}