{"k_neighbors": {"movie_id": "3.3 (weight)"}, "ratings": {"3031": "3", "214": "3", "199": "4", "1161": "3", "1261": "4", "5292": "1", "1347": "4", "4788": "3", "1300": "3", "2085": "5", "2051": "1", "user_id": "3.3", "1427": "3", "1851": "2", "4508": "2", "818": "1", "2907": "2", "2175": "5", "2015": "4", "1033": "4", "549": "1", "5964": "1", "2166": "4", "1316": "2", "618": "1", "4277": "3", "2461": "2", "1509": "4", "1150": "1", "306": "2", "1356": "4", "99": "2", "2244": "1", "2181": "4", "73": "3", "3520": "1", "2245": "3", "4448": "2", "3703": "1", "2931": "1", "1958": "1", "2212": "3", "787": "1", "1705": "4", "5830": "4", "783": "1", "19": "5", "2992": "4", "1556": "3", "2087": "1", "940": "2", "1181": "1", "1241": "4", "5599": "1", "2168": "4", "1943": "1", "1573": "3", "2063": "3", "1458": "1", "1767": "2", "2250": "3"}, "mean_rating": "3.3"}