{"k_neighbors": {"movie_id": "3.3 (weight)"}, "ratings": {"1147": "3", "5038": "2", "5394": "2", "889": "3", "3908": "3", "1345": "1", "3829": "3", "5077": "4", "5074": "2", "1052": "5", "user_id": "3.3", "1635": "5", "731": "4", "1692": "5", "1015": "5", "1291": "2", "3080": "5", "1698": "4", "1285": "3", "777": "3", "2913": "5", "3830": "4", "2916": "5", "3662": "1", "2857": "2", "1952": "4", "1836": "2", "1069": "4", "17": "3", "963": "3", "5241": "1", "864": "3", "928": "4", "2506": "1", "1242": "5", "1391": "1", "3985": "4", "1413": "3"}, "mean_rating": "3.3"}