{"k_neighbors": {"movie_id": "3.3 (weight)"}, "ratings": {"2597": "4", "5111": "3", "3808": "4", "3618": "2", "4048": "3", "1203": "2", "2986": "3", "3416": "4", "4513": "3", "5333": "4", "3958": "3", "3067": "3", "4789": "2", "4768": "5", "3328": "1", "4579": "3", "5643": "2", "2944": "4", "4227": "1", "user_id": "3.3", "5910": "4", "5744": "4", "3512": "3", "4934": "4", "3571": "4", "2383": "3", "4169": "3", "4708": "4", "2743": "4", "4957": "3", "2018": "4", "343": "5", "1119": "4", "549": "2", "4984": "3", "2878": "4", "4682": "3", "303": "2", "1150": "1", "3526": "5", "4467": "3", "4186": "3", "5483": "4", "4793": "1", "1069": "2", "1806": "5", "4055": "4", "4054": "2", "780": "3", "840": "4", "2230": "2", "6016": "4", "5305": "4", "53": "2", "4425": "3", "1680": "4", "4979": "3", "474": "3", "2258": "4", "3224": "4", "4580": "5", "5317": "4", "5974": "3"}, "mean_rating": "3.3"}